rediscollectiondb/__init__.py
rediscollectiondb/core.py
rediscollectiondb-0.1.2.dist-info/METADATA
rediscollectiondb-0.1.2.dist-info/WHEEL
rediscollectiondb-0.1.2.dist-info/top_level.txt
rediscollectiondb-0.1.2.dist-info/RECORD
