Metadata-Version: 2.1
Name: rediscollectiondb
Version: 0.1.2
Summary: A simple interface to manage collections in Redis.
Author: Guruh Purnama
Author-email: guruh@xgn.ai
Classifier: Programming Language :: Python :: 3
Classifier: License :: OSI Approved :: MIT License
Classifier: Operating System :: OS Independent
Requires-Python: >=3.6
Requires-Dist: redis
